jcamp.py
jcamp-1.3.0.dist-info/LICENSE.txt
jcamp-1.3.0.dist-info/WHEEL
jcamp-1.3.0.dist-info/METADATA
jcamp-1.3.0.dist-info/RECORD
