Metadata-Version: 2.1
Name: jcamp
Version: 1.3.0
Summary: A set of Python utilities for reading JCAMP-DX files.
Keywords: jcamp,jcamp-dx,spectra
Author-email: nzhagen <nh@hagenlab.org>
Requires-Python: >=3.8
Classifier: License :: OSI Approved :: MIT License
Classifier: Programming Language :: Python :: 3
Classifier: Operating System :: OS Independent
Classifier: Development Status :: 4 - Beta
Requires-Dist: datetime
Requires-Dist: numpy
Requires-Dist: re
Requires-Dist: pdb
Project-URL: Home, https://github.com/nzhagen/jcamp
